[
    {
        "name": "Say Time",
        "commands": [
            "how late",
            "what time is it",
            "current time",
            "what's the time",
            "tell me the time"
        ],
        "funcName": "sayTime"
    },
    {
        "name": "Stop",
        "commands": [
            "shop",
            "stock",
            "stop"
        ],
        "funcName": "stop"
    },
    {
        "name": "Repeat the user",
        "commands": [
            "repeat after me",
            "say it again"
        ],
        "funcName": "say"
    },
    {
        "name": "Greetings",
        "commands": [
            "good evening",
            "good afternoon",
            "good day",
            "hello",
            "hi",
            "hey",
            "greetings",
            "howdy",
            "good morning"
        ],
        "responses": [
            "hello",
            "hi there",
            "hi, nice to hear from you",
            "Hello! How can I assist you today?"
        ]
    },
    {
        "name": "Play Song",
        "commands": [
            "play a song",
            "play some music"
        ],
        "sound": "https://www.soundhelix.com/examples/mp3/SoundHelix-Song-1.mp3"
    },
    {
        "name": "Reload Commands",
        "commands": [
            "reload commands",
            "reload command",
            "reload"
        ],
        "funcName": "loadCommands"
    },
    {
        "name": "Toggle Mute",
        "commands": [
            "mute",
            "mute sound"
        ],
        "funcName": "toggleMute"
    },
    {
        "name": "Pause",
        "commands": [
            "pause"
        ],
        "funcName": "pause"
    },
    {
        "name": "Resume",
        "commands": [
            "resume",
            "continue"
        ],
        "funcName": "resume"
    },
    {
        "name": "Quit",
        "commands": [
            "shutdown",
            "shut down",
            "power off",
            "turn off"
        ],
        "funcName": "quit"
    },
    {
        "name": "Volume Up",
        "commands": [
            "volume up",
            "increase volume",
            "turn up the volume"
        ],
        "funcName": "volumeUp"
    },
    {
        "name": "Volume Down",
        "commands": [
            "volume down",
            "decrease volume",
            "turn down the volume"
        ],
        "funcName": "volumeDown"
    },
    {
        "name": "Set Volume",
        "commands": [
            "set volume to",
            "change volume to"
        ],
        "funcName": "setVolume"
    },
    {
        "name": "Tell Joke",
        "commands": [
            "tell me a joke",
            "tell a joke",
            "say a joke",
            "say something funny"
        ],
        "funcName": "tellJoke"
    },
    {
        "name": "Restart",
        "commands": [
            "restart"
        ],
        "funcName": "restart"
    },
    {
        "name": "Coin Toss",
        "commands": [
            "coin toss",
            "toss a coin",
            "flip a coin"
        ],
        "responses": [
            "Heads",
            "Tails",
            "You got Heads",
            "You got Tails",
            "It's Heads",
            "It's Tails"
        ]
    }
]
